estatistica/__init__.py
estatistica/funcoes/__init__.py
estatistica/funcoes/principal.py
package_estatistica-0.0.3.dist-info/METADATA
package_estatistica-0.0.3.dist-info/WHEEL
package_estatistica-0.0.3.dist-info/top_level.txt
package_estatistica-0.0.3.dist-info/RECORD
