Metadata-Version: 2.1
Name: package-estatistica
Version: 0.0.3
Summary: Engenheiro de dados e desenvolvedor de software
Home-page: https://github.com/alessandromirandagoncalves/package_estatistica.git
Author: Alessandro_Miranda_Goncalves
Author-email: alessandro.inovacao@gmail.com
License: UNKNOWN
Platform: UNKNOWN
Requires-Python: >=3.0
